sefcom_clusterutils/__init__.py
sefcom_clusterutils/utilization.py
sefcom_clusterutils-0.0.3.dist-info/entry_points.txt
sefcom_clusterutils-0.0.3.dist-info/LICENSE
sefcom_clusterutils-0.0.3.dist-info/WHEEL
sefcom_clusterutils-0.0.3.dist-info/METADATA
sefcom_clusterutils-0.0.3.dist-info/RECORD
