Metadata-Version: 2.1
Name: sefcom_clusterutils
Version: 0.0.3
Summary: Utilities for ASU SEFCOM's kubernetes cluster
Author-email: Kevin Phoenix <kevin@kphoenix.us>
Requires-Python: ~=3.8
Requires-Dist: kubernetes~=27.2.0
Requires-Dist: rich~=13.1.0
Project-URL: Home, https://github.com/sefcom/clusterutils
